Metadata-Version: 2.1
Name: gzinfo
Version: 1.0.1
Summary: Retrieving archive filename from gz files in Python 
Home-page: https://github.com/PierreSelim/gzinfo
Author: Pierre-Selim
Author-email: pierre-selim@huard.info
License: MIT Licence
Platform: UNKNOWN
Classifier: Programming Language :: Python :: 3.6
Classifier: Programming Language :: Python :: 3.7
Classifier: Programming Language :: Python :: 3.8
